LICENSE
MANIFEST.in
README.rst
setup.py
plottools/__init__.py
plottools/__main__.py
plottools/__version__.py
plottools/plottools.py
plottools/style.py
plottools.egg-info/PKG-INFO
plottools.egg-info/SOURCES.txt
plottools.egg-info/dependency_links.txt
plottools.egg-info/requires.txt
plottools.egg-info/top_level.txt
plottools/cm/__init__.py
plottools/cm/cm_blank.svg
plottools/cm/coldhot.py
plottools/cm/hotwater.py
plottools/cm/hotwater_new.py
plottools/cm/hotwater_old.py
plottools/cm/hue.py
plottools/cs/__init__.py
plottools/cs/colorscheme.py
plottools/cs/default.py
plottools/cs/util.py