Metadata-Version: 1.1
Name: plottools
Version: 0.2.0
Summary: UNKNOWN
Home-page: https://github.com/BrechtBa/plottools
Author: Brecht Baeten
Author-email: brecht.baeten@gmail.com
License: GPLv3
Platform: UNKNOWN
Classifier: Programming Language :: Python :: 2.7
